binance_data_downloader-0.2.0.dist-info/licenses/LICENSE
src/__init__.py
src/cli/__init__.py
src/cli/cli.py
src/directory_tree/__init__.py
src/directory_tree/base.py
src/directory_tree/binance.py
src/downloader/__init__.py
src/downloader/base.py
src/downloader/checksum.py
src/downloader/http_downloader.py
tests/__init__.py
tests/test_cli.py
tests/test_directory_tree.py
tests/test_downloader.py
binance_data_downloader-0.2.0.dist-info/METADATA
binance_data_downloader-0.2.0.dist-info/WHEEL
binance_data_downloader-0.2.0.dist-info/entry_points.txt
binance_data_downloader-0.2.0.dist-info/top_level.txt
binance_data_downloader-0.2.0.dist-info/RECORD
