Metadata-Version: 2.4
Name: binance-data-downloader
Version: 0.2.0
Summary: A command-line tool for downloading cryptocurrency data from Binance
Home-page: https://github.com/BaigeiMaster/binance-data-downloader
Author: Zhaorong Dai
Author-email: Zhaorong Dai <13710247598@163.com>
License: MIT
Project-URL: Homepage, https://github.com/ZhaorongDai/binance-data-downloader
Project-URL: Bug Tracker, https://github.com/ZhaorongDai/binance-data-downloader/issues
Keywords: cryptocurrency,data,downloader,binance
Classifier: Development Status :: 3 - Alpha
Classifier: Intended Audience :: Developers
Classifier: Programming Language :: Python :: 3
Classifier: Programming Language :: Python :: 3.8
Classifier: Programming Language :: Python :: 3.9
Classifier: Programming Language :: Python :: 3.10
Classifier: Programming Language :: Python :: 3.12
Requires-Python: >=3.8
License-File: LICENSE
Requires-Dist: aiofiles>=24.1.0
Requires-Dist: asyncio>=3.4.3
Requires-Dist: httpx>=0.28.1
Requires-Dist: loguru>=0.7.3
Requires-Dist: prompt-toolkit>=3.0.51
Requires-Dist: tqdm>=4.67.1
Requires-Dist: xmltodict>=0.14.2
Requires-Dist: zipfile36>=0.1.3
Dynamic: author
Dynamic: home-page
Dynamic: license-file
Dynamic: requires-python
